{
  "id": 1940669247291592852,
  "text": "יש סיכוי שאולי מכינים את הקרקע על מנת לפנות מתיישבים יהודים?\nלמה אני חושב כך? פשוט מאוד, דבר ראשון המון הסתה נגד ההתיישבות, עלילת דם חסרת ביסוס בכל האולפנים על סמך מילה של אדם אחד ששיקר ולבסוף אפס ראיות,\nילד בן 14 נורה ע\"י לוחמים קח לאט לאט מנרמלים ירי לעבר המתיישבים.\nלכאורה המג\"ד אמר לאחד החיילים שלו לצלם, איפה הסרטונים האלה הרי הוא אמר שתקפו אותם לא?\nמצרף לכם פה את הסרטון של המג\"ד אומר זאת. \nאה ונכון גם צהל פרסם סרטון של הזריקת אבנים לכאורה, מדובר בסרטון שצהל אמר ללוחמים לזרוק אבנים על מנת לתעד זאת, מצרף גם את התיעוד.",
  "author": "yedidya_epstien",
  "author_name": "ידידיה אפשטיין",
  "author_followers": 22507,
  "author_verified": false,
  "created_at": "2025-07-03 07:09:39+00:00",
  "retweet_count": 4,
  "like_count": 46,
  "reply_count": 2,
  "quote_count": 0,
  "view_count": 769,
  "url": "https://x.com/yedidya_epstien/status/1940669247291592852",
  "scraped_at": "2025-07-03 14:00:19.413734",
  "scraped_via": "telegram_bot"
}